{
  "_fv": 47,
  "_type": "recipe",
  "definition": {
    "recipeType": "Crafting",
    "recipeRetstackSize": 6,
    "group": "blocks",
    "cookingBookCategory": "MISC",
    "xpReward": 0.0,
    "cookingTime": 200,
    "craftingBookCategory": "BUILDING",
    "recipeShapeless": true,
    "recipeSlots": [
      {
        "value": ""
      },
      {
        "value": ""
      },
      {
        "value": ""
      },
      {
        "value": ""
      },
      {
        "value": ""
      },
      {
        "value": ""
      },
      {
        "value": "CUSTOM:ClassicDirtBlock"
      },
      {
        "value": "CUSTOM:ClassicDirtBlock"
      },
      {
        "value": "CUSTOM:ClassicDirtBlock"
      }
    ],
    "recipeReturnStack": {
      "value": "CUSTOM:ClassicDirtSlab"
    },
    "name": "classic_dirt_slab_recipe_1",
    "namespace": "mod"
  }
}